{
  "version": 1,
  "serviceConfiguration": {
    "apiName": "velpaAPI",
    "serviceName": "AppSync",
    "gqlSchemaPath": "C:\\Users\\mateo\\Desktop\\velpaNew\\amplify\\backend\\api\\velpaAPI\\schema.graphql",
    "defaultAuthType": {
      "mode": "AMAZON_COGNITO_USER_POOLS",
      "cognitoUserPoolId": "authvelpa01106a15"
    },
    "additionalAuthTypes": [
      {
        "mode": "API_KEY",
        "expirationTime": 365,
        "apiKeyExpirationDate": "2023-05-18T16:03:43.123Z",
        "keyDescription": ""
      }
    ],
    "conflictResolution": {
      "defaultResolutionStrategy": {
        "type": "AUTOMERGE"
      }
    }
  }
}